DataMemory.v
`timescale 1ns / 1ps

`define SIZE 1024

module DataMemory(ReadData , Address , WriteData , MemoryRead , MemoryWrite , Clock);
   input [63:0]      WriteData;
   input [63:0]      Address;
   input             Clock, MemoryRead, MemoryWrite;
   output reg [63:0] ReadData;

   reg [7:0] 	     memBank [`SIZE-1:0];


   // This task is used to write arbitrary data to the Data Memory by
   // the intialization block.
   task initset;
      input [63:0] addr;
      input [63:0] data;
      begin
	 memBank[addr] =  data[63:56] ; // Big-endian for the win...
	 memBank[addr+1] =  data[55:48];
	 memBank[addr+2] =  data[47:40];
	 memBank[addr+3] =  data[39:32];
	 memBank[addr+4] =  data[31:24];
	 memBank[addr+5] =  data[23:16];
	 memBank[addr+6] =  data[15:8];
	 memBank[addr+7] =  data[7:0];
      end
   endtask


   initial
     begin
        // preseting some data in the data memory used by test #1

        // Address 0x0 gets 0x1
        initset( 64'h0,  64'h1);  //Counter variable
        initset( 64'h8,  64'ha);  //Part of mask
        initset( 64'h10, 64'h5);  //Other part of mask
        initset( 64'h18, 64'h0ffbea7deadbeeff); //big constant
        initset( 64'h20, 64'h0); //clearing space

        // Add any data you need for your tests here.

     end

   // This always block reads the data memory and places a double word
   // on the ReadData bus.
   always @(posedge Clock)
     begin
        if(MemoryRead)
          begin
             ReadData[63:56] <=  memBank[Address];
             ReadData[55:48] <=  memBank[Address+1];
             ReadData[47:40] <=  memBank[Address+2];
             ReadData[39:32] <=  memBank[Address+3];
             ReadData[31:24] <=  memBank[Address+4];
             ReadData[23:16] <=  memBank[Address+5];
             ReadData[15:8] <=  memBank[Address+6];
             ReadData[7:0] <=  memBank[Address+7];
          end
     end

   // This always block takes data from the WriteData bus and writes
   // it into the DataMemory.
   always @(posedge Clock)
     begin
        if(MemoryWrite)
          begin
             memBank[Address] <= #3 WriteData[63:56] ;
             memBank[Address+1] <= #3 WriteData[55:48];
             memBank[Address+2] <= #3 WriteData[47:40];
             memBank[Address+3] <= #3 WriteData[39:32];
             memBank[Address+4] <= #3 WriteData[31:24];
             memBank[Address+5] <= #3 WriteData[23:16];
             memBank[Address+6] <= #3 WriteData[15:8];
             memBank[Address+7] <= #3 WriteData[7:0];
             // Could be useful for debugging:
             $display("Writing Address:%h Data:%h",Address, WriteData);
          end
     end
endmodule

ALU.v
`define AND   4'b0000
`define OR    4'b0001
`define ADD   4'b0010
`define SUB   4'b0110
`define PassB 4'b0111


module ALU(BusW, BusA, BusB, ALUCtrl, Zero);
    
    output  [63:0] BusW;
    input   [63:0] BusA, BusB;
    input   [3:0] ALUCtrl;
    output  Zero;
    
    reg     [63:0] BusW;
    reg     Zero;
    
    always @(ALUCtrl or BusA or BusB) begin
        case(ALUCtrl)
            `AND: begin
                BusW = BusA & BusB;   
            end
            `OR: begin
                BusW = BusA | BusB;
            end
            `ADD: begin
                BusW = BusA + BusB;
                 //$display("%h + %h = %h",BusA,BusB, BusW);
            end
            `SUB: begin
                BusW = BusA - BusB;
            end
            `PassB: begin
                BusW = BusB;
            end
        endcase
        
        if(BusW == 0) begin
            Zero = 1;
        end else begin
            Zero = 0;
        end
            
    end

endmodule

NextPClogic.v
module NextPClogic(NextPC, CurrentPC, SignExtImm64, Branch, ALUZero, Uncondbranch); 
   input [63:0] CurrentPC, SignExtImm64;    // state your input at 64 bits for currentPC and sign extender
   input 	Branch, ALUZero, Uncondbranch;   // state your inputs for the Branch, ALU, and unconditional branch
   output reg [63:0] NextPC;                 // register output for NextPC as 64 bits

   

   /* write your code here */ 
   always@(*) begin
      if((Branch == 1'b1) && (ALUZero == 1'b1)) begin   // check that Branch and ALU are 1 or ON
         NextPC = CurrentPC + (SignExtImm64 <<< 2);                   // shift NextPC with sign extender by 2 to the left
      end else if(Uncondbranch == 1'b1) begin           // otherwise Undonditional branch is ON
         NextPC = CurrentPC + (SignExtImm64 <<< 2);                   // complete the sign extend shift left by 2   
      end else begin
         NextPC = CurrentPC + 4;                        // otherwise it can only set the NextPC to the next one from CurrentPC
      end

   end                                                  // end the loop


endmodule                                               // endmodule

RegisterFile.v
module RegisterFile(BusA, BusB, BusW, RA, RB, RW, RegWr, Clk);
    output [63:0] BusA;        // set the BusA output to 64 bits
    output [63:0] BusB;        // set the BusB output to 64 bits
    input [63:0] BusW;         // set the BusW output to 64 bits
    input [4:0] RW, RA, RB;    // set RW, RA, and RB inputs to 5 bits
    input RegWr;               // set input register write
    input Clk;                  // set input for clock
    reg [63:0] registers [31:0];   // set register of a 32-64 bit registers
     
    assign #2 BusA = (RA == 5'd31) ? 0 : registers[RA]; // assignment of BusA to register RA after waiting 2 time units
    assign #2 BusB = (RB == 5'd31) ? 0 : registers[RB]; // assignment of BusB to register RB after waiting 2 time units
    //initial registers[31] = 64'h0;  // initiliaze register 31 as 0
     
     /*
    always@(Clk)begin
        registers[31] <= #4 64'h0;
    end
    */
    always @ (negedge Clk) begin      // negative edge of clock to initiaite loop
        if(RegWr)                     // Check RegisterWrite is occuring
            registers[RW] <= #3 BusW;  // Access register RW and waits 3 time units, then writes BusW 
            //registers[31] <= #4 64'h0; // Ensure X31 is always 0 and waits 4 time units
    end                                // end the loop
endmodule                               // end the module

SignExtender.v
module SignExtender(Out64, In26, Ctrl, LSL); 
    output reg [63:0] Out64; 
    input [25:0] In26; 
    input [2:0] Ctrl; 
    input [1:0] LSL;

    reg extBit; 
    //reg [63:0] Out64; 
    //reg [25:0] In26; 
    //reg [1:0] Ctrl; 

/*
    // 00 I-type
    assign extBit = (Ctrl ? 2'b00 : In26[21]);
    assign Out64 = (Ctrl ? 2'b00 : {{52{extBit}}, In26[21:10]});

    // 01 D-type    
    assign extBit = (Ctrl ? 2'b01 : In26[20]);
    assign Out64 = (Ctrl ? 2'b01 : {{55{extBit}}, In26[20:12]});

    // 10 B-type
    assign extBit = (Ctrl ? 2'b10 : In26[25]);
    assign Out64 = (Ctrl ? 2'b10 : {{38{extBit}}, In26[25:0]});

    // 11 CB-type
    assign extBit = (Ctrl ? 2'b11 : In26[23]);
    assign Out64 = (Ctrl ? 2'b11 : {{45{extBit}}, In26[23:5]});
*/
    always@(*) begin
    case(Ctrl) 
        3'b000   :   begin
                        extBit = In26[21];
                        Out64 = {{52{extBit}}, In26[21:10]};
                        end
        3'b001   :   begin
                        extBit = In26[20];
                        Out64 = {{55{extBit}}, In26[20:12]};
                        end
        3'b010   :   begin
                        extBit = In26[25];
                        Out64 = {{38{extBit}}, In26[25:0]};
                        end
        3'b011   :   begin
                        extBit = In26[23];
                        Out64 = {{45{extBit}}, In26[23:5]};
                        end
        3'b100   :   begin
                        extBit = In26[20];
                        case(LSL)
                            2'b00   :   Out64 = {{48'b0}, In26[20:5]};
                            2'b01   :   Out64 = {{32'b0}, In26[20:5], 16'b0};
                            2'b10   :   Out64 = {{16'b0}, In26[20:5], 32'b0};
                            2'b11   :   Out64 = {In26[20:5], 48'b0};
                        endcase
                        end
        
    endcase
    end
 
endmodule

SingleCycleControl.v
`define OPCODE_ANDREG 11'b?0001010???
`define OPCODE_ORRREG 11'b?0101010???
`define OPCODE_ADDREG 11'b?0?01011???
`define OPCODE_SUBREG 11'b?1?01011???

`define OPCODE_ADDIMM 11'b?0?10001???
`define OPCODE_SUBIMM 11'b?1?10001???

`define OPCODE_MOVZ   11'b110100101??

`define OPCODE_B      11'b?00101?????
`define OPCODE_CBZ    11'b?011010????

`define OPCODE_LDUR   11'b??111000010
`define OPCODE_STUR   11'b??111000000

module control(
	       output reg 	reg2loc,
	       output reg 	alusrc,
	       output reg 	mem2reg,
	       output reg 	regwrite,
	       output reg 	memread,
	       output reg 	memwrite,
	       output reg 	branch,
	       output reg 	uncond_branch,
	       output reg [3:0] aluop,
	       output reg [2:0] signop,
	       input [10:0] 	opcode
	       );

   always @(*)
     begin
	casez (opcode)

          /* Add cases here for each instruction your processor supports */
	  `OPCODE_ANDREG: begin
	       reg2loc       = 1'b0;
               alusrc        = 1'b0;
               mem2reg       = 1'b0;
               regwrite      = 1'b1;
               memread       = 1'b0;
               memwrite      = 1'b0;
               branch        = 1'b0;
               uncond_branch = 1'b0;
               aluop         = 4'b0000;
               signop        = 3'bxxx;
            end
	    
	  `OPCODE_ORRREG: begin
	       reg2loc       = 1'b0;
               alusrc        = 1'b0;
               mem2reg       = 1'b0;
               regwrite      = 1'b1;
               memread       = 1'b0;
               memwrite      = 1'b0;
               branch        = 1'b0;
               uncond_branch = 1'b0;
               aluop         = 4'b0001;
               signop        = 3'bxxx;
            end
	  `OPCODE_ADDREG: begin
	       reg2loc       = 1'b0;
               alusrc        = 1'b0;
               mem2reg       = 1'b0;
               regwrite      = 1'b1;
               memread       = 1'b0;
               memwrite      = 1'b0;
               branch        = 1'b0;
               uncond_branch = 1'b0;
               aluop         = 4'b0010;
               signop        = 3'bxxx;
            end
	  `OPCODE_SUBREG: begin
	       reg2loc       = 1'b0;
               alusrc        = 1'b0;
               mem2reg       = 1'b0;
               regwrite      = 1'b1;
               memread       = 1'b0;
               memwrite      = 1'b0;
               branch        = 1'b0;
               uncond_branch = 1'b0;
               aluop         = 4'b0110;
               signop        = 3'bxxx;
            end
	  `OPCODE_ADDIMM: begin
	       reg2loc       = 1'bx;
               alusrc        = 1'b1;
               mem2reg       = 1'b0;
               regwrite      = 1'b1;
               memread       = 1'b0;
               memwrite      = 1'b0;
               branch        = 1'b0;
               uncond_branch = 1'b0;
               aluop         = 4'b0010; 
               signop        = 3'b000; 
            end
	  `OPCODE_SUBIMM: begin
	       reg2loc       = 1'bx;
               alusrc        = 1'b1;
               mem2reg       = 1'b0;
               regwrite      = 1'b1;
               memread       = 1'b0;
               memwrite      = 1'b0;
               branch        = 1'b0;
               uncond_branch = 1'b0;
               aluop         = 4'b0110;
               signop        = 3'b000;
            end
	  `OPCODE_MOVZ: begin
	       reg2loc       = 1'bx;
               alusrc        = 1'b1;
               mem2reg       = 1'b0;
               regwrite      = 1'b1;
               memread       = 1'b0;
               memwrite      = 1'b0;
               branch        = 1'b0;
               uncond_branch = 1'b0;
               aluop         = 4'b0111;
               signop        = 3'b100;
            end
	  `OPCODE_B: begin
	       reg2loc       = 1'bx;
               alusrc        = 1'bx;
               mem2reg       = 1'bx;
               regwrite      = 1'b0;
               memread       = 1'b0;
               memwrite      = 1'b0;
               branch        = 1'bx;
               uncond_branch = 1'b1;
               aluop         = 4'bxxxx;
               signop        = 3'b010;
            end
	  `OPCODE_CBZ: begin
	       reg2loc       = 1'b1;
               alusrc        = 1'b0;
               mem2reg       = 1'bx;
               regwrite      = 1'b0;
               memread       = 1'b0;
               memwrite      = 1'b0;
               branch        = 1'b1;
               uncond_branch = 1'b0;
               aluop         = 4'b0111;
               signop        = 3'b011;
            end
	  `OPCODE_LDUR: begin
	       reg2loc       = 1'bx;
               alusrc        = 1'b1;
               mem2reg       = 1'b1;
               regwrite      = 1'b1;
               memread       = 1'b1;
               memwrite      = 1'b0;
               branch        = 1'b0;
               uncond_branch = 1'b0;
               aluop         = 4'b0010;
               signop        = 3'b001;
            end
	  `OPCODE_STUR: begin
	       reg2loc       = 1'b1;
               alusrc        = 1'b1;
               mem2reg       = 1'bx;
               regwrite      = 1'b0;
               memread       = 1'b0;
               memwrite      = 1'b1;
               branch        = 1'b0;
               uncond_branch = 1'b0;
               aluop         = 4'b0010;
               signop        = 3'b001;
            end

          default:
            begin
               reg2loc       = 1'bx;
               alusrc        = 1'bx;
               mem2reg       = 1'bx;
               regwrite      = 1'b0;
               memread       = 1'b0;
               memwrite      = 1'b0;
               branch        = 1'b0;
               uncond_branch = 1'b0;
               aluop         = 4'bxxxx;
               signop        = 2'bxx;
            end
	endcase
     end

endmodule

InstructionMemory.v
`timescale 1ns / 1ps
/*
 * Module: InstructionMemory
 *
 * Implements read-only instruction memory
 * 
 */
module InstructionMemory(Data, Address);
   parameter T_rd = 20;
   parameter MemSize = 40;
   
   output [31:0] Data;
   input [63:0]  Address;
   reg [31:0] 	 Data;
   
   /*
    * ECEN 350 Processor Test Functions
    * Texas A&M University
    */
   
   always @ (Address) begin

      case(Address)

	/* Test Program 1:
	 * Program loads constants from the data memory. Uses these constants to test
	 * the following instructions: LDUR, ORR, AND, CBZ, ADD, SUB, STUR and B.
	 * 
	 * Assembly code for test:
	 * 
	 * 0: LDUR X9, [XZR, 0x0]    //Load 1 into x9
	 * 4: LDUR X10, [XZR, 0x8]   //Load a into x10
	 * 8: LDUR X11, [XZR, 0x10]  //Load 5 into x11
	 * C: LDUR X12, [XZR, 0x18]  //Load big constant into x12
	 * 10: LDUR X13, [XZR, 0x20]  //load a 0 into X13
	 * 
	 * 14: ORR X10, X10, X11  //Create mask of 0xf
	 * 18: AND X12, X12, X10  //Mask off low order bits of big constant
	 * 
	 * loop:
	 * 1C: CBZ X12, end  //while X12 is not 0
	 * 20: ADD X13, X13, X9  //Increment counter in X13
	 * 24: SUB X12, X12, X9  //Decrement remainder of big constant in X12
	 * 28: B loop  //Repeat till X12 is 0
	 * 2C: STUR X13, [XZR, 0x20]  //store back the counter value into the memory location 0x20
	 */
	

	63'h000: Data = 32'hF84003E9;
	63'h004: Data = 32'hF84083EA;
	63'h008: Data = 32'hF84103EB;
	63'h00c: Data = 32'hF84183EC;
	63'h010: Data = 32'hF84203ED;
	63'h014: Data = 32'hAA0B014A;
	63'h018: Data = 32'h8A0A018C;
	63'h01c: Data = 32'hB400008C;
	63'h020: Data = 32'h8B0901AD;
	63'h024: Data = 32'hCB09018C;
	63'h028: Data = 32'h17FFFFFD;
	63'h02c: Data = 32'hF80203ED;
	63'h030: Data = 32'hF84203ED;  //One last load to place stored value on memdbus for test checking.

	/* Add code for your tests here */



	/* Test Program 2 (student made):
	 * 1. Use the MOVZ instruction, and any other instructions needed, to construct the following constant 0x123456789abcdef0 in register X9.
	 * 2. Store this immediate value to memory at memory address 0x28
	 * 3. Load this value back to register X10 
	 * 
	 * Assembly code for test:
	 * 
     * 0: MOVZ X1, 0x1234, LSL 48
     * 4: MOVZ X2, 0x5678, LSL 32
     * 8: MOVZ X3, 0x9ABC, LSL 16
     * C: MOVZ X9, 0xDEF0, LSL 0
     * 10: ADD X9, X9, X3
     * 14: ADD X9, X9, X2
     * 18: ADD X9, X9, X1
     * 1C: STUR X9, [XZR, 0x28]
     * 20: LDUR X10, [XZR, 0x28]
	 */
	
	63'h034: Data = 32'b11010010111000100100011010000001;
	63'h038: Data = 32'b11010010110010101100111100000010;
	63'h03c: Data = 32'b11010010101100110101011110000011;
	63'h040: Data = 32'b11010010100110111101111000001001;
	63'h044: Data = 32'b00001011000000110000000100101001;
	63'h048: Data = 32'b00001011000000100000000100101001;
	63'h04c: Data = 32'b00001011000000010000000100101001;
	63'h050: Data = 32'b11111000000000101000001111101001;
	63'h054: Data = 32'b11111000010000101000001111101010;

	
	default: Data = 32'hXXXXXXXX;
      endcase
   end
endmodule

SingleCycleProc.v
`include "InstructionMemory.v"
`include "SingleCycleControl.v"
`include "SignExtender.v"
`include "RegisterFile.v"
`include "NextPClogic.v"
`include "ALU.v"
`include "DataMemory.v"

module singlecycle(
		   input 	     resetl,
		   input [63:0]      startpc,
		   output reg [63:0] currentpc,


		   output [63:0]     MemtoRegOut,  // this should be
						   // attached to the
						   // output of the
						   // MemtoReg Mux
        
		   input 	     CLK
		   );

   // Next PC connections
   wire [63:0] 			     nextpc;       // The next PC, to be updated on clock cycle

   // Instruction Memory connections
   wire [31:0] 			     instruction;  // The current instruction

   // Parts of instruction
   wire [4:0] 			     rd;            // The destination register
   wire [4:0] 			     rm;            // Operand 1
   wire [4:0] 			     rn;            // Operand 2
   wire [10:0] 			     opcode;

   // Control wires
   wire 			     reg2loc;
   wire 			     alusrc;
   wire 			     mem2reg;
   wire 			     regwrite;
   wire 			     memread;
   wire 			     memwrite;
   wire 			     branch;
   wire 			     uncond_branch;
   wire [3:0] 			     aluctrl;
   wire [2:0] 			     signop;

   // Register file connections
   wire [63:0] 			     regoutA;     // Output A
   wire [63:0] 			     regoutB;     // Output B

   // ALU connections
   wire [63:0] 			     aluout;
   wire 			     zero;
   wire [63:0] aluB;
   

   // Sign Extender connections
   wire [63:0] 			     extimm;

   // Data Memory connections
   wire [63:0] ReadData;
   wire [63:0] MemtoRegOutWire;


   // PC update logic
   always @(negedge CLK)
     begin
        if (resetl)
          currentpc <= #3 nextpc;
        else
          currentpc <= #3 startpc;
     end

   // Parts of instruction
   assign rd = instruction[4:0];
   assign rm = instruction[9:5];
   assign rn = reg2loc ? instruction[4:0] : instruction[20:16];
   assign opcode = instruction[31:21];

   /*
    * Connect the remaining datapath elements below.
    * Do not forget any additional multiplexers that may be required.
    */
   InstructionMemory imem(
			  .Data(instruction),
			  .Address(currentpc)
			  );

   control cont(
		   .reg2loc(reg2loc),
		   .alusrc(alusrc),
		   .mem2reg(mem2reg),
		   .regwrite(regwrite),
		   .memread(memread),
		   .memwrite(memwrite),
		   .branch(branch),
		   .uncond_branch(uncond_branch),
		   .aluop(aluctrl),
		   .signop(signop),
		   .opcode(opcode)
		   );

   SignExtender signextnd(
       .Out64(extimm),
       .In26(instruction[25:0]),
       .Ctrl(signop),
       .LSL(instruction[22:21])
       ); 
  
   RegisterFile registers(
			 .BusA(regoutA),
			 .BusB(regoutB),
			 .BusW(MemtoRegOut), 
       .RA(rm), 
       .RB(rn),
       .RW(rd),
       .RegWr(regwrite),
       .Clk(CLK)
       );

   NextPClogic pclogic(
       .NextPC(nextpc),
       .CurrentPC(currentpc),
       .SignExtImm64(extimm),
       .Branch(branch),
       .ALUZero(zero),
       .Uncondbranch(uncond_branch)
       );

   assign aluB = (alusrc) ? extimm : regoutB;
   ALU alu(
       .BusW(aluout),
       .BusA(regoutA),
       .BusB(aluB),
       .ALUCtrl(aluctrl),
       .Zero(zero)
       );
    

   DataMemory DataMem(
       .ReadData(ReadData), 
       .Address(aluout), 
       .WriteData(regoutB), 
       .MemoryRead(memread), 
       .MemoryWrite(memwrite),
       .Clock(CLK)
       );
   assign MemtoRegOutWire = (mem2reg) ? ReadData : aluout;
   assign MemtoRegOut = MemtoRegOutWire;

endmodule

SingleCycleProcTest.v
`timescale 1ns / 1ps

`define STRLEN 32
`define HalfClockPeriod 60
`define ClockPeriod `HalfClockPeriod * 2

module SingleCycleProcTest_v;

   initial
     begin
        $dumpfile("singlecycle.vcd");
        $dumpvars;
     end

   // These tasks are used to check if a given test has passed and
   // confirm that all tests passed.
   task passTest;
      input [63:0] actualOut, expectedOut;
      input [`STRLEN*8:0] testType;
      inout [7:0] 	  passed;

      if(actualOut == expectedOut) begin $display ("%s passed", testType); passed = passed + 1; end
      else $display ("%s failed: 0x%x should be 0x%x", testType, actualOut, expectedOut);
   endtask

   task allPassed;
      input [7:0] passed;
      input [7:0] numTests;

      if(passed == numTests) $display ("All tests passed");
      else $display("Some tests failed: %d of %d passed", passed, numTests);
   endtask

   // Inputs
   reg 		  CLK;
   reg 		  Reset_L;
   reg [63:0] 	  startPC;
   reg [7:0] 	  passed;
   reg [15:0] 	  watchdog;

   // Outputs
   wire [63:0] 	  MemtoRegOut;
   wire [63:0] 	  currentPC;

   // Instantiate the Unit Under Test (UUT)
   singlecycle uut (
		    .CLK(CLK),
		    .resetl(Reset_L),
		    .startpc(startPC),
		    .currentpc(currentPC),
		    .MemtoRegOut(MemtoRegOut)
		    );

   initial begin
      // Initialize Inputs
      Reset_L = 1;
      startPC = 0;
      passed = 0;

      // Initialize Watchdog timer
      watchdog = 0;

      // Wait for global reset
      #(1 * `ClockPeriod);

      // Program 1
      #1
        Reset_L = 0; startPC = 0;
      @(posedge CLK);
      @(negedge CLK);
      @(posedge CLK);
      Reset_L = 1;

      // ***********************************************************
      // This while loop will continue cycling the processor until the
      // PC reaches the final instruction in the first test.  If the
      // program forms an infinite loop, never reaching the end, the
      // watchdog timer will kick in and kill simulation after 64K
      // cycles.
      // ***********************************************************

      while (currentPC < 64'h30)
        begin
	   @(posedge CLK);
	   @(negedge CLK);
           $display("CurrentPC:%h",currentPC);
        end
      passTest(MemtoRegOut, 64'hF, "Results of Program 1", passed);

      // ***********************************************************
      // Add your new tests here
      // ***********************************************************

      while (currentPC < 64'h54)
         begin
         @(posedge CLK);
         @(negedge CLK);
            $display("CurrentPC:%h",currentPC);
         end
      passTest(MemtoRegOut, 64'h123456789ABCDEF0, "Results of Program 2", passed);
      // Done
      allPassed(passed, 2);   // Be sure to change the one to match
      // the number of tests you add.
      $finish;
   end

   // Initialize the clock to be 0
   initial begin
      CLK = 0;
   end

   // The following is correct if clock starts at LOW level at StartTime //
   always begin
      #`HalfClockPeriod CLK = ~CLK;
      #`HalfClockPeriod CLK = ~CLK;
      watchdog = watchdog +1;
   end

   // Kill the simulation if the watchdog hits 64K cycles
   always @*
     if (watchdog == 16'hFF)
       begin
          $display("Watchdog Timer Expired.");
          $finish;
       end


endmodule

singlecycle.vcd
$date
	Wed Jan 24 11:56:57 2024
$end
$version
	Icarus Verilog
$end
$timescale
	1ps
$end
$scope module SingleCycleProcTest_v $end
$var wire 64 ! currentPC [63:0] $end
$var wire 64 " MemtoRegOut [63:0] $end
$var reg 1 # CLK $end
$var reg 1 $ Reset_L $end
$var reg 8 % passed [7:0] $end
$var reg 64 & startPC [63:0] $end
$var reg 16 ' watchdog [15:0] $end
$scope module uut $end
$var wire 1 # CLK $end
$var wire 64 ( MemtoRegOut [63:0] $end
$var wire 1 $ resetl $end
$var wire 64 ) startpc [63:0] $end
$var wire 1 * zero $end
$var wire 1 + uncond_branch $end
$var wire 3 , signop [2:0] $end
$var wire 5 - rn [4:0] $end
$var wire 5 . rm [4:0] $end
$var wire 1 / regwrite $end
$var wire 64 0 regoutB [63:0] $end
$var wire 64 1 regoutA [63:0] $end
$var wire 1 2 reg2loc $end
$var wire 5 3 rd [4:0] $end
$var wire 11 4 opcode [10:0] $end
$var wire 64 5 nextpc [63:0] $end
$var wire 1 6 memwrite $end
$var wire 1 7 memread $end
$var wire 1 8 mem2reg $end
$var wire 32 9 instruction [31:0] $end
$var wire 64 : extimm [63:0] $end
$var wire 1 ; branch $end
$var wire 1 < alusrc $end
$var wire 64 = aluout [63:0] $end
$var wire 4 > aluctrl [3:0] $end
$var wire 64 ? aluB [63:0] $end
$var wire 64 @ ReadData [63:0] $end
$var wire 64 A MemtoRegOutWire [63:0] $end
$var reg 64 B currentpc [63:0] $end
$scope module DataMem $end
$var wire 1 # Clock $end
$var wire 64 C WriteData [63:0] $end
$var wire 1 6 MemoryWrite $end
$var wire 1 7 MemoryRead $end
$var wire 64 D Address [63:0] $end
$var reg 64 E ReadData [63:0] $end
$scope task initset $end
$var reg 64 F addr [63:0] $end
$var reg 64 G data [63:0] $end
$upscope $end
$upscope $end
$scope module alu $end
$var wire 64 H BusB [63:0] $end
$var wire 64 I BusA [63:0] $end
$var wire 4 J ALUCtrl [3:0] $end
$var reg 64 K BusW [63:0] $end
$var reg 1 * Zero $end
$upscope $end
$scope module cont $end
$var wire 11 L opcode [10:0] $end
$var reg 4 M aluop [3:0] $end
$var reg 1 < alusrc $end
$var reg 1 ; branch $end
$var reg 1 8 mem2reg $end
$var reg 1 7 memread $end
$var reg 1 6 memwrite $end
$var reg 1 2 reg2loc $end
$var reg 1 / regwrite $end
$var reg 3 N signop [2:0] $end
$var reg 1 + uncond_branch $end
$upscope $end
$scope module imem $end
$var wire 64 O Address [63:0] $end
$var reg 32 P Data [31:0] $end
$upscope $end
$scope module pclogic $end
$var wire 1 * ALUZero $end
$var wire 1 ; Branch $end
$var wire 64 Q CurrentPC [63:0] $end
$var wire 1 + Uncondbranch $end
$var wire 64 R SignExtImm64 [63:0] $end
$var reg 64 S NextPC [63:0] $end
$upscope $end
$scope module registers $end
$var wire 64 T BusW [63:0] $end
$var wire 1 # Clk $end
$var wire 5 U RA [4:0] $end
$var wire 5 V RB [4:0] $end
$var wire 5 W RW [4:0] $end
$var wire 1 / RegWr $end
$var wire 64 X BusB [63:0] $end
$var wire 64 Y BusA [63:0] $end
$upscope $end
$scope module signextnd $end
$var wire 3 Z Ctrl [2:0] $end
$var wire 26 [ In26 [25:0] $end
$var wire 2 \ LSL [1:0] $end
$var reg 64 ] Out64 [63:0] $end
$var reg 1 ^ extBit $end
$upscope $end
$upscope $end
$scope task allPassed $end
$var reg 8 _ numTests [7:0] $end
$var reg 8 ` passed [7:0] $end
$upscope $end
$scope task passTest $end
$var reg 64 a actualOut [63:0] $end
$var reg 64 b expectedOut [63:0] $end
$var reg 8 c passed [7:0] $end
$var reg 257 d testType [256:0] $end
$upscope $end
$upscope $end
$enddefinitions $end
#0
$dumpvars
bx d
bx c
bx b
bx a
bx `
bx _
x^
bx ]
bx \
bx [
bx Z
bx Y
bx X
bx W
bx V
bx U
bx T
bx S
bx R
bx Q
bx P
bx O
bx N
bx M
bx L
bx K
bx J
bx I
bx H
b0 G
b100000 F
bx E
bx D
bx C
bx B
bx A
bx @
bx ?
bx >
bx =
x<
x;
bx :
bx 9
x8
x7
x6
bx 5
bx 4
bx 3
x2
bx 1
bx 0
x/
bx .
bx -
bx ,
x+
x*
b0 )
bx (
b0 '
b0 &
b0 %
1$
0#
bx "
bx !
$end
#60000
1#
#120000
b1 '
0#
#121000
0$
#180000
1#
#240000
b10 '
0#
#243000
0*
b0 ?
b0 H
b0 :
b0 R
b0 ]
0^
b1 ,
b1 N
b1 Z
b10 >
b10 J
b10 M
0+
0;
06
17
1/
18
1<
b0x00x -
b0x00x V
b10 \
b10000000000001111101001 [
b11111000010 4
b11111000010 L
b11111 .
b11111 U
b1001 3
b1001 W
b11111000010000000000001111101001 9
b11111000010000000000001111101001 P
b100 5
b100 S
b0 !
b0 B
b0 O
b0 Q
#245000
1*
b0 =
b0 D
b0 K
b0 1
b0 I
b0 Y
#300000
b1 "
b1 (
b1 T
b1 A
b1 @
b1 E
1$
1#
#360000
b11 '
0#
#363000
0*
b1000 =
b1000 D
b1000 K
b1000 ?
b1000 H
b1000 :
b1000 R
b1000 ]
b0x0x0 -
b0x0x0 V
b10000001000001111101010 [
b1010 3
b1010 W
b11111000010000001000001111101010 9
b11111000010000001000001111101010 P
b1000 5
b1000 S
b100 !
b100 B
b100 O
b100 Q
#420000
b1010 "
b1010 (
b1010 T
b1010 A
b1010 @
b1010 E
1#
#480000
b100 '
0#
#483000
b10000 =
b10000 D
b10000 K
b10000 ?
b10000 H
b10000 :
b10000 R
b10000 ]
b0x0x1 -
b0x0x1 V
b10000010000001111101011 [
b1011 3
b1011 W
b11111000010000010000001111101011 9
b11111000010000010000001111101011 P
b1100 5
b1100 S
b1000 !
b1000 B
b1000 O
b1000 Q
#540000
b101 "
b101 (
b101 T
b101 A
b101 @
b101 E
1#
#600000
b101 '
0#
#603000
b11000 =
b11000 D
b11000 K
b11000 ?
b11000 H
b11000 :
b11000 R
b11000 ]
b0xx0x -
b0xx0x V
b10000011000001111101100 [
b1100 3
b1100 W
b11111000010000011000001111101100 9
b11111000010000011000001111101100 P
b10000 5
b10000 S
b1100 !
b1100 B
b1100 O
b1100 Q
#660000
b111111111011111010100111110111101010110110111110111011111111 "
b111111111011111010100111110111101010110110111110111011111111 (
b111111111011111010100111110111101010110110111110111011111111 T
b111111111011111010100111110111101010110110111110111011111111 A
b111111111011111010100111110111101010110110111110111011111111 @
b111111111011111010100111110111101010110110111110111011111111 E
1#
#720000
b110 '
0#
#723000
b100000 =
b100000 D
b100000 K
b100000 ?
b100000 H
b100000 :
b100000 R
b100000 ]
b0xxxx -
b0xxxx V
b10000100000001111101101 [
b1101 3
b1101 W
b11111000010000100000001111101101 9
b11111000010000100000001111101101 P
b10100 5
b10100 S
b10000 !
b10000 B
b10000 O
b10000 Q
#780000
b0 "
b0 (
b0 T
b0 A
b0 @
b0 E
1#
#840000
b111 '
0#
#843000
bx =
bx D
bx K
bx "
bx (
bx T
bx A
bx ?
bx H
bx ,
bx N
bx Z
b1 >
b1 J
b1 M
07
08
0<
02
b1011 -
b1011 V
b0 \
b10000010110000000101001010 [
b10101010000 4
b10101010000 L
b1010 .
b1010 U
b1010 3
b1010 W
b10101010000010110000000101001010 9
b10101010000010110000000101001010 P
b11000 5
b11000 S
b10100 !
b10100 B
b10100 O
b10100 Q
#845000
b1111 "
b1111 (
b1111 T
b1111 A
b101 ?
b101 H
b1111 =
b1111 D
b1111 K
b101 0
b101 C
b101 X
b1010 1
b1010 I
b1010 Y
#900000
1#
#960000
b1000 '
0#
#963000
b0 "
b0 (
b0 T
b0 A
1*
b0 =
b0 D
b0 K
b0 >
b0 J
b0 M
b1010 -
b1010 V
b10000010100000000110001100 [
b10001010000 4
b10001010000 L
b1100 .
b1100 U
b1100 3
b1100 W
b10001010000010100000000110001100 9
b10001010000010100000000110001100 P
b11100 5
b11100 S
b11000 !
b11000 B
b11000 O
b11000 Q
#965000
b1111 "
b1111 (
b1111 T
b1111 A
b1111 ?
b1111 H
0*
b1111 =
b1111 D
b1111 K
b1111 0
b1111 C
b1111 X
b111111111011111010100111110111101010110110111110111011111111 1
b111111111011111010100111110111101010110110111110111011111111 I
b111111111011111010100111110111101010110110111110111011111111 Y
#1020000
1#
#1080000
b1001 '
0#
#1083000
b0xxxx "
b0xxxx (
b0xxxx T
b0xxxx A
b100 :
b100 R
b100 ]
b11 ,
b11 N
b11 Z
b111 >
b111 J
b111 M
1;
0/
x8
12
b1100 -
b1100 V
b10001100 [
b10110100000 4
b10110100000 L
b100 .
b100 U
b10110100000000000000000010001100 9
b10110100000000000000000010001100 P
b100000 5
b100000 S
b11100 !
b11100 B
b11100 O
b11100 Q
#1085000
bx 1
bx I
bx Y
#1140000
1#
#1200000
b1010 '
0#
